dawis/__init__.py
dawis/anscombe_transforms.py
dawis/atrous.py
dawis/congrid.py
dawis/datacube.py
dawis/exceptions.py
dawis/gif.py
dawis/hard_threshold.py
dawis/label_regions.py
dawis/make_interscale_trees.py
dawis/make_regions.py
dawis/restore_objects.py
dawis/synthesis_by_analysis.py
dawis/table_noise_stds.py
dawis/test.py
dawis/wavelet_transforms.py
dawis/gallery/tidal_group_f814w_sci.fits
dawis-0.0.4.dist-info/LICENSE
dawis-0.0.4.dist-info/METADATA
dawis-0.0.4.dist-info/WHEEL
dawis-0.0.4.dist-info/top_level.txt
dawis-0.0.4.dist-info/RECORD
